pyqqq/__init__.py
pyqqq/backtest/__init__.py
pyqqq/backtest/broker.py
pyqqq/backtest/environment.py
pyqqq/backtest/logger.py
pyqqq/backtest/positionprovider.py
pyqqq/backtest/strategy.py
pyqqq/backtest/utils.py
pyqqq/backtest/wallclock.py
pyqqq/brokerage/__init__.py
pyqqq/brokerage/ebest/__init__.py
pyqqq/brokerage/ebest/domestic_stock.py
pyqqq/brokerage/ebest/oauth.py
pyqqq/brokerage/ebest/simple.py
pyqqq/brokerage/ebest/tr_client.py
pyqqq/brokerage/helper.py
pyqqq/brokerage/kis/__init__.py
pyqqq/brokerage/kis/domestic_stock.py
pyqqq/brokerage/kis/oauth.py
pyqqq/brokerage/kis/overseas_stock.py
pyqqq/brokerage/kis/simple.py
pyqqq/brokerage/kis/simple_overseas.py
pyqqq/brokerage/kis/tr_client.py
pyqqq/brokerage/multiprocess_tracker.py
pyqqq/brokerage/tracker.py
pyqqq/config.py
pyqqq/data/__init__.py
pyqqq/data/daily.py
pyqqq/data/domestic.py
pyqqq/data/index.py
pyqqq/data/minutes.py
pyqqq/data/overseas.py
pyqqq/data/realtime.py
pyqqq/data/ticks.py
pyqqq/data/us_stocks.py
pyqqq/datatypes.py
pyqqq/executors/__init__.py
pyqqq/executors/hook.py
pyqqq/utils/__init__.py
pyqqq/utils/api_client.py
pyqqq/utils/array.py
pyqqq/utils/backoff.py
pyqqq/utils/casting.py
pyqqq/utils/compute.py
pyqqq/utils/copycat.py
pyqqq/utils/daily_tickers.py
pyqqq/utils/display.py
pyqqq/utils/indicators.py
pyqqq/utils/kvstore.py
pyqqq/utils/limiter.py
pyqqq/utils/local_cache.py
pyqqq/utils/logger.py
pyqqq/utils/market_schedule.py
pyqqq/utils/mock_api.py
pyqqq/utils/position_classifier.py
pyqqq/utils/retry.py
pyqqq/utils/singleton.py
pyqqq-0.12.223.dist-info/METADATA
pyqqq-0.12.223.dist-info/WHEEL
pyqqq-0.12.223.dist-info/RECORD
